packing_packages/__init__.py
packing_packages/__main__.py
packing_packages/constants.py
packing_packages/helpers/__init__.py
packing_packages/helpers/_helpers.py
packing_packages/install/__init__.py
packing_packages/install/__main__.py
packing_packages/install/_core.py
packing_packages/logging/__init__.py
packing_packages/logging/_logging.py
packing_packages/pack/__init__.py
packing_packages/pack/__main__.py
packing_packages/pack/_core.py
packing_packages/pack/_types.py
packing_packages/pack/_utils.py
packing_packages/pack/yaml/__init__.py
packing_packages/pack/yaml/__main__.py
packing_packages/pack/yaml/_core.py
packing_packages/pack/yaml/constants.py
packing_packages-0.4.0.dist-info/licenses/LICENSE
packing_packages-0.4.0.dist-info/METADATA
packing_packages-0.4.0.dist-info/WHEEL
packing_packages-0.4.0.dist-info/entry_points.txt
packing_packages-0.4.0.dist-info/top_level.txt
packing_packages-0.4.0.dist-info/RECORD
