Metadata-Version: 2.4
Name: packing-packages
Version: 0.4.0
Summary: This module provides functionality to pack conda environments and their dependencies into a specified directory.
Author: yu9824
Maintainer: yu9824
License-Expression: MIT
Project-URL: Homepage, https://github.com/yu9824/packing-packages
Project-URL: Documentation, https://yu9824.github.io/packing-packages/
Project-URL: PyPI, https://pypi.org/project/packing-packages/
Project-URL: Source, https://github.com/yu9824/packing-packages
Project-URL: Tracker, https://github.com/yu9824/packing-packages/issues
Keywords: anaconda,conda
Classifier: Programming Language :: Python :: 3
Classifier: Programming Language :: Python :: 3.9
Classifier: Programming Language :: Python :: 3.10
Classifier: Programming Language :: Python :: 3.11
Classifier: Programming Language :: Python :: 3.12
Classifier: Programming Language :: Python :: 3.13
Classifier: Programming Language :: Python :: 3.14
Requires-Python: >=3.9
License-File: LICENSE
Provides-Extra: test
Requires-Dist: pytest; extra == "test"
Provides-Extra: dev
Requires-Dist: build; extra == "dev"
Provides-Extra: optional
Requires-Dist: colorlog; extra == "optional"
Requires-Dist: tqdm; extra == "optional"
Requires-Dist: PyYAML; extra == "optional"
Provides-Extra: docs
Requires-Dist: sphinx; extra == "docs"
Requires-Dist: myst-parser; extra == "docs"
Requires-Dist: myst-nb; extra == "docs"
Requires-Dist: sphinx-book-theme; extra == "docs"
Requires-Dist: jupyter-sphinx; extra == "docs"
Dynamic: license-file
